mambo_minhhai/__init__.py
mambo_minhhai/forward_operator/__init__.py
mambo_minhhai/forward_operator/operator.py
mambo_minhhai/utils/__init__.py
mambo_minhhai/utils/config.py
mambo_minhhai/utils/display_utils.py
mambo_minhhai/utils/latex_utils.py
mambo_minhhai/utils/model_utils.py
mambo_minhhai/utils/tensor_utils.py
mambo_minhhai-0.0a214.dist-info/METADATA
mambo_minhhai-0.0a214.dist-info/WHEEL
mambo_minhhai-0.0a214.dist-info/RECORD
