Metadata-Version: 2.1
Name: mambo_minhhai
Version: 0.0a214
Summary: A small example package
Project-URL: Homepage, https://bitbucket.org/these-mhnguyen/mambo/src/master/
Project-URL: Issues, https://bitbucket.org/these-mhnguyen/mambo/src/master/
Author-email: Minh Hai NGUYEN <nguyenhai7120qh@gmail.com>
Classifier: License :: OSI Approved :: MIT License
Classifier: Operating System :: OS Independent
Classifier: Programming Language :: Python :: 3
Requires-Python: >=3.8
Requires-Dist: einops
Requires-Dist: matplotlib
Requires-Dist: ml-collections
Requires-Dist: numpy
Requires-Dist: torch
Requires-Dist: torchvision
Requires-Dist: yaml
